github_downloader/__init__.py
github_downloader/github_downloader.py
github_downloader/test_github_downloader.py
github_downloader/version.py
github_downloader-0.1.0.dist-info/LICENSE
github_downloader-0.1.0.dist-info/METADATA
github_downloader-0.1.0.dist-info/WHEEL
github_downloader-0.1.0.dist-info/top_level.txt
github_downloader-0.1.0.dist-info/RECORD
